carto_cli/__init__.py
carto_cli/carto_batch.py
carto_cli/carto_dataset.py
carto_cli/carto_env.py
carto_cli/carto_sql.py
carto_cli/utils.py
carto_cli/carto/__init__.py
carto_cli/carto/carto_user.py
carto_cli/carto/queries.py
carto_cli/carto/version.py
carto_cli/commands/__init__.py
carto_cli/commands/batch/__init__.py
carto_cli/commands/batch/job.py
carto_cli/commands/dataset/__init__.py
carto_cli/commands/dataset/dataset.py
carto_cli/commands/sql/__init__.py
carto_cli/commands/sql/execute_sql.py
carto_cli/commands/sql/running_queries.py
carto_cli-0.0.5.dist-info/METADATA
carto_cli-0.0.5.dist-info/RECORD
carto_cli-0.0.5.dist-info/WHEEL
carto_cli-0.0.5.dist-info/entry_points.txt
carto_cli-0.0.5.dist-info/top_level.txt
