Metadata-Version: 2.1
Name: carto-cli
Version: 0.0.5
Summary: Command Line applications to interact with your CARTO account
Home-page: https://github.com/jsanz/carto_cli
Author: Jorge Sanz
Author-email: xurxosanz@gmail.com
License: MIT
Keywords: carto cli cartodb api
Platform: UNKNOWN
Classifier: License :: OSI Approved :: MIT License
Classifier: Programming Language :: Python :: 3
Classifier: Programming Language :: Python :: 3.7
Requires-Dist: carto (==1.3.0)
Requires-Dist: click (==6.7)
Requires-Dist: PyYAML (==3.12)
Requires-Dist: prettytable (==0.7.2)
